ifc2duckdb/__init__.py
ifc2duckdb/cli.py
ifc2duckdb/patcher.py
ifc2duckdb/py.typed
ifc2duckdb/version.py
ifc2duckdb-0.1.2.dist-info/licenses/LICENSE
ifc2duckdb-0.1.2.dist-info/METADATA
ifc2duckdb-0.1.2.dist-info/WHEEL
ifc2duckdb-0.1.2.dist-info/entry_points.txt
ifc2duckdb-0.1.2.dist-info/top_level.txt
ifc2duckdb-0.1.2.dist-info/RECORD
