Metadata-Version: 2.4
Name: ifc2duckdb
Version: 0.1.2
Summary: Convert IFC files to DuckDB format for fast analysis and querying
Author-email: chuongmep <chuongpqvn@gmail.com>
Maintainer-email: chuongmep <chuongpqvn@gmail.com>
License-Expression: LGPL-3.0-or-later
Project-URL: Homepage, https://github.com/chuongmep/ifc-2-duckdb
Project-URL: Documentation, https://github.com/chuongmep/ifc-2-duckdb#readme
Project-URL: Repository, https://github.com/chuongmep/ifc-2-duckdb
Project-URL: Bug Tracker, https://github.com/chuongmep/ifc-2-duckdb/issues
Keywords: ifc,duckdb,building-information-modeling,bim,database,conversion
Classifier: Development Status :: 4 - Beta
Classifier: Intended Audience :: Developers
Classifier: Intended Audience :: Science/Research
Classifier: Topic :: Scientific/Engineering
Classifier: Topic :: Database
Classifier: Programming Language :: Python :: 3
Classifier: Programming Language :: Python :: 3.10
Classifier: Programming Language :: Python :: 3.11
Classifier: Programming Language :: Python :: 3.12
Classifier: Operating System :: OS Independent
Requires-Python: >=3.10
License-File: LICENSE
Requires-Dist: ifcopenshell>=0.8.0
Requires-Dist: duckdb>=0.7.0
Requires-Dist: numpy>=1.20.0
Requires-Dist: ifcpatch>=0.1.0
Provides-Extra: dev
Requires-Dist: pytest>=7.0.0; extra == "dev"
Requires-Dist: pytest-cov>=4.0.0; extra == "dev"
Requires-Dist: black>=22.0.0; extra == "dev"
Requires-Dist: flake8>=5.0.0; extra == "dev"
Requires-Dist: isort>=5.12.0; extra == "dev"
Requires-Dist: mypy>=1.0.0; extra == "dev"
Requires-Dist: pre-commit>=2.20.0; extra == "dev"
Provides-Extra: docs
Requires-Dist: sphinx>=5.0.0; extra == "docs"
Requires-Dist: sphinx-rtd-theme>=1.0.0; extra == "docs"
Requires-Dist: myst-parser>=0.18.0; extra == "docs"
Dynamic: license-file
